README.rst
setup.py
tests/__init__.py
tests/integration/__init__.py
tests/integration/test_topic.py
tests/unit/__init__.py
tests/unit/test_handler.py
tests/unit/test_identifier.py
tests/unit/test_messages.py
tests/unit/test_processors.py
tests/unit/test_session.py
tests/unit/test_topic.py
tests/unit/test_utils.py
tests/unit/processors/__init__.py
tests/unit/processors/test_pubsub.py
tests/unit/processors/test_pubsub_customize.py
tests/unit/processors/test_rpc.py
tornwamp/__init__.py
tornwamp/customize.py
tornwamp/handler.py
tornwamp/identifier.py
tornwamp/messages.py
tornwamp/session.py
tornwamp/utils.py
tornwamp.egg-info/PKG-INFO
tornwamp.egg-info/SOURCES.txt
tornwamp.egg-info/dependency_links.txt
tornwamp.egg-info/requires.txt
tornwamp.egg-info/top_level.txt
tornwamp/processors/__init__.py
tornwamp/processors/pubsub/__init__.py
tornwamp/processors/pubsub/customize.py
tornwamp/processors/rpc/__init__.py
tornwamp/processors/rpc/customize.py
tornwamp/topic/__init__.py
tornwamp/topic/customize.py