Metadata-Version: 1.1
Name: tornwamp
Version: 2.0.0
Summary: WAMP (Web Application Messaging Protocol) utilities
Home-page: http://github.com/ef-ctx/tornwamp
Author: Tatiana Al-Chueyr Martins
Author-email: tatiana.alchueyr@gmail.com
License: Apache License
Download-URL: http://pypi.python.org/pypi/tornwamp
Platform: UNKNOWN
Classifier: Development Status :: 4 - Beta
Classifier: Environment :: Web Environment
Classifier: Intended Audience :: Developers
Classifier: License :: OSI Approved :: Apache Software License
Classifier: Operating System :: OS Independent
Classifier: Programming Language :: Python
Classifier: Programming Language :: Python :: 2.7
Classifier: Programming Language :: Python :: 3
Classifier: Programming Language :: Python :: 3.5
